vbagent/__init__.py
vbagent/agents/__init__.py
vbagent/agents/alternate.py
vbagent/agents/base.py
vbagent/agents/clarity_checker.py
vbagent/agents/classifier.py
vbagent/agents/converter.py
vbagent/agents/grammar_checker.py
vbagent/agents/idea.py
vbagent/agents/multi_variant.py
vbagent/agents/reviewer.py
vbagent/agents/scanner.py
vbagent/agents/selector.py
vbagent/agents/solution_checker.py
vbagent/agents/tikz.py
vbagent/agents/tikz_checker.py
vbagent/agents/variant.py
vbagent/cli/__init__.py
vbagent/cli/alternate.py
vbagent/cli/batch.py
vbagent/cli/check.py
vbagent/cli/classify.py
vbagent/cli/common.py
vbagent/cli/config.py
vbagent/cli/convert.py
vbagent/cli/idea.py
vbagent/cli/main.py
vbagent/cli/process.py
vbagent/cli/ref.py
vbagent/cli/scan.py
vbagent/cli/tikz.py
vbagent/cli/variant.py
vbagent/config.py
vbagent/models/__init__.py
vbagent/models/batch.py
vbagent/models/classification.py
vbagent/models/diff.py
vbagent/models/idea.py
vbagent/models/pipeline.py
vbagent/models/review.py
vbagent/models/scan.py
vbagent/models/version_store.py
vbagent/prompts/__init__.py
vbagent/prompts/alternate.py
vbagent/prompts/clarity_checker.py
vbagent/prompts/classifier.py
vbagent/prompts/converter.py
vbagent/prompts/grammar_checker.py
vbagent/prompts/idea.py
vbagent/prompts/reviewer.py
vbagent/prompts/scanner/__init__.py
vbagent/prompts/scanner/assertion_reason.py
vbagent/prompts/scanner/common.py
vbagent/prompts/scanner/match.py
vbagent/prompts/scanner/mcq_mc.py
vbagent/prompts/scanner/mcq_sc.py
vbagent/prompts/scanner/passage.py
vbagent/prompts/scanner/subjective.py
vbagent/prompts/solution_checker.py
vbagent/prompts/tikz.py
vbagent/prompts/tikz_checker.py
vbagent/prompts/variants/__init__.py
vbagent/prompts/variants/conceptual.py
vbagent/prompts/variants/conceptual_calculus.py
vbagent/prompts/variants/context.py
vbagent/prompts/variants/multi_context.py
vbagent/prompts/variants/numerical.py
vbagent/references/__init__.py
vbagent/references/context.py
vbagent-0.1.1.dist-info/METADATA
vbagent-0.1.1.dist-info/WHEEL
vbagent-0.1.1.dist-info/entry_points.txt
vbagent-0.1.1.dist-info/RECORD
