Metadata-Version: 2.3
Name: vbagent
Version: 0.1.1
Summary: CLI tool for physics question image scanning, categorization, and variant generation
Author: vaibhavblayer
Author-email: vaibhavblayer@gmail.com
Requires-Python: >=3.12
Classifier: Programming Language :: Python :: 3
Classifier: Programming Language :: Python :: 3.12
Classifier: Programming Language :: Python :: 3.13
Provides-Extra: dev
Requires-Dist: click (>=8.1.0)
Requires-Dist: hypothesis (>=6.0.0) ; extra == "dev"
Requires-Dist: openai-agents (>=0.6.2)
Requires-Dist: pillow (>=10.0.0)
Requires-Dist: pydantic (>=2.0.0)
Requires-Dist: pytest (>=8.0.0) ; extra == "dev"
Requires-Dist: rich (>=13.0.0)
